djimporter/__init__.py
djimporter/apps.py
djimporter/checks.py
djimporter/fields.py
djimporter/forms.py
djimporter/importers.py
djimporter/models.py
djimporter/tasks.py
djimporter/urls.py
djimporter/views.py
djimporter/migrations/0001_initial.py
djimporter/migrations/0002_alter_importlog_user.py
djimporter/migrations/0003_alter_importlog_status.py
djimporter/migrations/0004_importlog_progress.py
djimporter/migrations/__init__.py
djimporter/static/djimporter/js/guess_csv_properties.js
djimporter/static/djimporter/js/upload_status.js
djimporter/templates/djimporter/base.example.html
djimporter/templates/djimporter/base.html
djimporter/templates/djimporter/importer_info.html
djimporter/templates/djimporter/importlog_confirm_delete.html
djimporter/templates/djimporter/importlog_detail.html
djimporter/templates/djimporter/importlog_detail_extended.html
djimporter/templates/djimporter/importlog_list.html
djimporter-0.10.dist-info/licenses/LICENSE
tests/__init__.py
tests/conftest.py
tests/models.py
tests/requirements.txt
tests/test_csvmodels.py
tests/test_logs.py
tests/urls.py
tests/data/ForeignKeySource.csv
tests/data/ForeignKeySource_valid.csv
tests/data/albums.csv
tests/data/songs.csv
djimporter-0.10.dist-info/METADATA
djimporter-0.10.dist-info/WHEEL
djimporter-0.10.dist-info/top_level.txt
djimporter-0.10.dist-info/RECORD
